leadingzero2.sv
module lzsv(
	input wire clk,
	input wire [24:0] v,

	output wire [7:0] num,
	output wire [23:0] res
);

// {num8, res24}
 reg [31:0] cnum;
 assign num = cnum[31:24];
 assign res = cnum[23:0];

always @(posedge clk) begin
	if (v[24]) cnum <= {8'hFF, v[24:1]};
	else if (v[23]) cnum <= {8'd0, v[23:0]};
	else if (v[22]) cnum <= {8'd1, v[22:0],  1'b0};
	else if (v[21]) cnum <= {8'd2, v[21:0],  2'b0};
	else if (v[20]) cnum <= {8'd3, v[20:0],  3'b0};
	else if (v[19]) cnum <= {8'd4, v[19:0],  4'b0};
	else if (v[18]) cnum <= {8'd5, v[18:0],  5'b0};
	else if (v[17]) cnum <= {8'd6, v[17:0],  6'b0};
	else if (v[16]) cnum <= {8'd7, v[16:0],  7'b0};
	else if (v[15]) cnum <= {8'd8, v[15:0],  8'b0};
	else if (v[14]) cnum <= {8'd9, v[14:0],  9'b0};
	else if (v[13]) cnum <= {8'd10, v[13:0], 10'b0};
	else if (v[12]) cnum <= {8'd11, v[12:0], 11'b0};
	else if (v[11]) cnum <= {8'd12, v[11:0], 12'b0};
	else if (v[10]) cnum <= {8'd13, v[10:0], 13'b0};
	else if (v[ 9]) cnum <= {8'd14, v[ 9:0], 14'b0};
	else if (v[ 8]) cnum <= {8'd15, v[ 8:0], 15'b0};
	else if (v[ 7]) cnum <= {8'd16, v[ 7:0], 16'b0};
	else if (v[ 6]) cnum <= {8'd17, v[ 6:0], 17'b0};
	else if (v[ 5]) cnum <= {8'd18, v[ 5:0], 18'b0};
	else if (v[ 4]) cnum <= {8'd19, v[ 4:0], 19'b0};
	else if (v[ 3]) cnum <= {8'd20, v[ 3:0], 20'b0};
	else if (v[ 2]) cnum <= {8'd21, v[ 2:0], 21'b0};
	else if (v[ 1]) cnum <= {8'd22, v[ 1:0], 22'b0};
	else if (v[ 0]) cnum <= {8'd23, 24'h800_000};
	else cnum <= {8'd24, 24'd0};
end

endmodule

float_add2.sv
module float_add(
	input wire clk,
	input wire [31:0] v1,
	input wire [31:0] v2,

	output wire [31:0] vres
);

	assign vres = res;

	//TIM1
	reg [31:0] vb;
	reg [31:0] vs;

	//TIM2
	reg [7:0] dexp;
	reg [7:0] vexp;
	reg [22:0] vb2;
	reg [22:0] vs2;
	
	//TIM3
	reg [7:0] vexp2;
	reg [24:0] vb3;
	reg [24:0] vs3;
	
	//TIM4
	reg [7:0] vexp3;
	reg [24:0] r;

	//TIM5,6
	reg [7:0] vexp4;
	reg [7:0] vexp5;
	reg [23:0] lzr;
	wire [7:0] lznum;
	wire [23:0] lzres;

	lzsv lzm(
		.clk(clk),
		.v(r),
		.num(lznum),
		.res(lzres)
	);

	//TIM7
	reg [31:0] res;

	always @(posedge clk) begin
		
		// TIM1 //
		if (v2[30:23] < v1[30:23]) begin
			vb <= v1;
			vs <= v2;
		end else if (v1[30:23] < v2[30:23]) begin
			vb <= v2;
			vs <= v1;
		end else if (v2[22:0] < v1[22:0]) begin
			vb <= v1;
			vs <= v2;
		end else begin
			vb <= v2;
			vs <= v1;
		end

		// TIM2 //
		dexp <= vb[30:23] - vs[30:23];
		vexp <= vb[30:23];

		vb2 <= vb;
		vs2 <= vs;

		// TIM3 //
		vexp2 <= vexp;
		
		vb3 <= {2'b1, vb2};
		vs3 <= {1'b0, vssf({1'b1, vs2}, dexp)};

		// TIM4 //
		vexp3 <= vexp2;

//		r <= vb3 + vs3;
	r <= vb3 - vs3;

		// TIM5 //
		vexp4 <= vexp3;
		vexp5 <= vexp4 - lznum;
		
		lzr <= lzres;

		// TIM6 //
		res[31] <= 1'b0;
		res[30:23] <= vexp5;
		res[22:0] <= lzr[22:0];
	
	end

//Value Small Shift Function
function [23:0] vssf(input [23:0] v, input [7:0] num);
begin
  case(num)
  8'd0: vssf = v;
  8'd1: vssf = {1'b0, v[23:1]};
  8'd2: vssf = {2'b0, v[23:2]};
  8'd3: vssf = {3'b0, v[23:3]};
  8'd4: vssf = {4'b0, v[23:4]};

  8'd5: vssf = {5'b0, v[23:5]};
  8'd6: vssf = {6'b0, v[23:6]};
  8'd7: vssf = {7'b0, v[23:7]};
  8'd8: vssf = {8'b0, v[23:8]};
  8'd9: vssf = {9'b0, v[23:9]};

  8'd10: vssf = {10'b0, v[23:10]};
  8'd11: vssf = {11'b0, v[23:11]};
  8'd12: vssf = {12'b0, v[23:12]};
  8'd13: vssf = {13'b0, v[23:13]};
  8'd14: vssf = {14'b0, v[23:14]};

  8'd15: vssf = {15'b0, v[23:15]};
  8'd16: vssf = {16'b0, v[23:16]};
  8'd17: vssf = {17'b0, v[23:17]};
  8'd18: vssf = {18'b0, v[23:18]};
  8'd19: vssf = {19'b0, v[23:19]};

  8'd20: vssf = {20'b0, v[23:20]};
  8'd21: vssf = {21'b0, v[23:21]};
  8'd22: vssf = {22'b0, v[23:22]};
  8'd23: vssf = {23'b0, v[23]};
  default: vssf = 24'b0;
  endcase
end
endfunction

endmodule

addsim.v
`timescale 1ps/1ps
module addsim();

  reg clk;
  wire [31:0] res;
  wire [31:0] v1 = 32'h42F6_CCCD; //123.4
  wire [31:0] v2 = 32'h40E8_0000; //7.25

	float_add fa(
		.clk(clk),
		.v1(v1),
		.v2(v2),
		.vres(res)
	);

  initial begin
    clk = 0;
    forever #1 clk = ~clk;
  end

 integer i;  
  initial begin
    $dumpfile("addsim.vcd");
    $dumpvars(0, addsim);
    $monitor ("%t: clk = %b", $time, clk);
  end

  initial begin
    #20 $finish();
  end

endmodule

addsim.vcd
$date
	Sat May 16 20:50:42 2020
$end
$version
	Icarus Verilog
$end
$timescale
	1ps
$end
$scope module addsim $end
$var wire 32 ! v1 [31:0] $end
$var wire 32 " v2 [31:0] $end
$var wire 32 # res [31:0] $end
$var reg 1 $ clk $end
$scope module fa $end
$var wire 1 $ clk $end
$var wire 32 % v1 [31:0] $end
$var wire 32 & v2 [31:0] $end
$var wire 32 ' vres [31:0] $end
$var wire 24 ( lzres [23:0] $end
$var wire 8 ) lznum [7:0] $end
$var reg 8 * dexp [7:0] $end
$var reg 24 + lzr [23:0] $end
$var reg 25 , r [24:0] $end
$var reg 32 - res [31:0] $end
$var reg 32 . vb [31:0] $end
$var reg 23 / vb2 [22:0] $end
$var reg 25 0 vb3 [24:0] $end
$var reg 8 1 vexp [7:0] $end
$var reg 8 2 vexp2 [7:0] $end
$var reg 8 3 vexp3 [7:0] $end
$var reg 8 4 vexp4 [7:0] $end
$var reg 8 5 vexp5 [7:0] $end
$var reg 32 6 vs [31:0] $end
$var reg 23 7 vs2 [22:0] $end
$var reg 25 8 vs3 [24:0] $end
$scope function vssf $end
$var reg 8 9 num [7:0] $end
$var reg 24 : v [23:0] $end
$var reg 24 ; vssf [23:0] $end
$upscope $end
$scope module lzm $end
$var wire 1 $ clk $end
$var wire 25 < v [24:0] $end
$var wire 24 = res [23:0] $end
$var wire 8 > num [7:0] $end
$var reg 32 ? cnum [31:0] $end
$upscope $end
$upscope $end
$upscope $end
$enddefinitions $end
#0
$dumpvars
bx ?
bx >
bx =
bx <
bx ;
bx :
bx 9
bx 8
bx 7
bx 6
bx 5
bx 4
bx 3
bx 2
bx 1
bx 0
bx /
bx .
bx -
bx ,
bx +
bx *
bx )
bx (
bx '
b1000000111010000000000000000000 &
b1000010111101101100110011001101 %
0$
bx #
b1000000111010000000000000000000 "
b1000010111101101100110011001101 !
$end
#1
b11000 )
b11000 >
b0 (
b0 =
b11000000000000000000000000000 ?
b0xxxxxxxxxxxxxxxxxxxxxxxxxxxxxxx #
b0xxxxxxxxxxxxxxxxxxxxxxxxxxxxxxx '
b0xxxxxxxxxxxxxxxxxxxxxxxxxxxxxxx -
b0 8
b1xxxxxxxxxxxxxxxxxxxxxxx 0
b1000000111010000000000000000000 6
b1000010111101101100110011001101 .
b0 ;
b1xxxxxxxxxxxxxxxxxxxxxxx :
1$
#2
0$
#3
b0 +
b11010000000000000000000 7
b11101101100110011001101 /
b10000101 1
b100 *
1$
#4
0$
#5
b0xxxxxxxx00000000000000000000000 #
b0xxxxxxxx00000000000000000000000 '
b0xxxxxxxx00000000000000000000000 -
b11101000000000000000 8
b111101101100110011001101 0
b10000101 2
b11101000000000000000 ;
b111010000000000000000000 :
b100 9
1$
#6
0$
#7
b111010000100110011001101 ,
b111010000100110011001101 <
b10000101 3
1$
#8
0$
#9
b0 )
b0 >
b111010000100110011001101 (
b111010000100110011001101 =
b111010000100110011001101 ?
b10000101 4
1$
#10
0$
#11
b111010000100110011001101 +
b10000101 5
1$
#12
0$
#13
b1000010111010000100110011001101 #
b1000010111010000100110011001101 '
b1000010111010000100110011001101 -
1$
