float_add.sv
module float_add(
	input wire clk,
	input wire [31:0] v1,
	input wire [31:0] v2,

	output wire [31:0] res
);

	wire [7:0] exp1 = v1[30:23];
	wire [7:0] exp2 = v2[30:23];

	wire [22:0] fra1 = v1[22:0];
	wire [22:0] fra2 = v2[22:0];

	assign res = 32'h0;

	reg [31:0] vb;
	reg [31:0] vs;
	reg [24:0] vb2;
	reg [24:0] vs2;
	reg [24:0] r1;

	reg [7:0] dexp;

	always @(posedge clk) begin
		if (exp2 < exp1) begin
			vb <= v1;
			vs <= v2;
		end else if (exp1 < exp2) begin
			vb <= v2;
			vs <= v1;
		end else begin
			if (fra2 < fra1) begin
				vb <= v1;
				vs <= v2;
			end else begin
				vb <= v2;
				vs <= v1;
			end
		end

		dexp <= vb[30:23] - vs[30:23];

		vb2 <= {2'b10, vb[22:0]};
		vs2 <= {1'b0, vssf({1'b1, vs[22:0]}, dexp)};

		r1 <= vb2 + vs2;
		

	end


//Value Small Shift Function
function [23:0] vssf(input [23:0] v, input [7:0] num);
begin
  case(num)
  8'd0: vssf = v;
  8'd1: vssf = {1'b0, v[23:1]};
  8'd2: vssf = {2'b0, v[23:2]};
  8'd3: vssf = {3'b0, v[23:3]};
  8'd4: vssf = {4'b0, v[23:4]};

  8'd5: vssf = {5'b0, v[23:5]};
  8'd6: vssf = {6'b0, v[23:6]};
  8'd7: vssf = {7'b0, v[23:7]};
  8'd8: vssf = {8'b0, v[23:8]};
  8'd9: vssf = {9'b0, v[23:9]};

  8'd10: vssf = {10'b0, v[23:10]};
  8'd11: vssf = {11'b0, v[23:11]};
  8'd12: vssf = {12'b0, v[23:12]};
  8'd13: vssf = {13'b0, v[23:13]};
  8'd14: vssf = {14'b0, v[23:14]};

  8'd15: vssf = {15'b0, v[23:15]};
  8'd16: vssf = {16'b0, v[23:16]};
  8'd17: vssf = {17'b0, v[23:17]};
  8'd18: vssf = {18'b0, v[23:18]};
  8'd19: vssf = {19'b0, v[23:19]};

  8'd20: vssf = {20'b0, v[23:20]};
  8'd21: vssf = {21'b0, v[23:21]};
  8'd22: vssf = {22'b0, v[23:22]};
  8'd23: vssf = {23'b0, v[23]};
  default: vssf = 24'b0;
  endcase
end
endfunction




endmodule

fpsim.v
`timescale 1ps/1ps
module fpu_sim();

  reg clk;
  wire [31:0] res;
  reg [7:0] acnt;

	always @(posedge clk) begin
		acnt <= acnt + 8'b1;
	end

	float_add fa(
		.clk(clk),
		.v1({1'b0, acnt, 23'h00_1234}),
		.v2({1'b0, 8'd127, 23'h00_1000}),
		.res(res)
	);

  initial begin
    clk = 0;
		acnt <= 8'b0;
    forever #10 clk = ~clk;
  end

 integer i;  
  initial begin
    $dumpfile("fpus.vcd");
    $dumpvars(0, fpu_sim);
//    for(i = 0;i < 2**FIFO_DEPTH;i++)
//      $dumpvars(1,u0.data[i]);
    $monitor ("%t: clk = %b", $time, clk);
  end

  initial begin
    #5000 $finish();
  end

endmodule

fpus.vcd
$date
	Thu Apr  9 17:04:35 2020
$end
$version
	Icarus Verilog
$end
$timescale
	1ps
$end
$scope module fpu_sim $end
$var wire 32 ! res [31:0] $end
$var reg 8 " acnt [7:0] $end
$var reg 1 # clk $end
$scope module fa $end
$var wire 1 # clk $end
$var wire 32 $ res [31:0] $end
$var wire 32 % v1 [31:0] $end
$var wire 32 & v2 [31:0] $end
$var wire 23 ' fra2 [22:0] $end
$var wire 23 ( fra1 [22:0] $end
$var wire 8 ) exp2 [7:0] $end
$var wire 8 * exp1 [7:0] $end
$var reg 8 + dexp [7:0] $end
$var reg 25 , r1 [24:0] $end
$var reg 32 - vb [31:0] $end
$var reg 25 . vb2 [24:0] $end
$var reg 32 / vs [31:0] $end
$var reg 25 0 vs2 [24:0] $end
$scope function vssf $end
$var reg 8 1 num [7:0] $end
$var reg 24 2 v [23:0] $end
$var reg 24 3 vssf [23:0] $end
$upscope $end
$upscope $end
$upscope $end
$enddefinitions $end
#0
$dumpvars
bx 3
bx 2
bx 1
bx 0
bx /
bx .
bx -
bx ,
bx +
b0 *
b1111111 )
b1001000110100 (
b1000000000000 '
b111111100000000001000000000000 &
b1001000110100 %
b0 $
0#
b0 "
b0 !
$end
#10
b1 *
b0 0
b10xxxxxxxxxxxxxxxxxxxxxxx .
b1001000110100 /
b111111100000000001000000000000 -
b100000000001001000110100 %
b1 "
b0 3
b1xxxxxxxxxxxxxxxxxxxxxxx 2
1#
#20
0#
#30
b10 *
b1000000000001001000110100 %
b10 "
b1000000000001000000000000 .
b1111111 +
b100000000001001000110100 /
b100000000001001000110100 2
1#
#40
0#
#50
b11 *
b1000000000001000000000000 ,
b1111110 +
b1000000000001001000110100 /
b1100000000001001000110100 %
b11 "
b1111111 1
1#
#60
0#
#70
b100 *
b10000000000001001000110100 %
b100 "
b1111101 +
b1100000000001001000110100 /
b1111110 1
1#
#80
0#
#90
b101 *
b1111100 +
b10000000000001001000110100 /
b10100000000001001000110100 %
b101 "
b1111101 1
1#
#100
0#
#110
b110 *
b11000000000001001000110100 %
b110 "
b1111011 +
b10100000000001001000110100 /
b1111100 1
1#
#120
0#
#130
b111 *
b1111010 +
b11000000000001001000110100 /
b11100000000001001000110100 %
b111 "
b1111011 1
1#
#140
0#
#150
b1000 *
b100000000000001001000110100 %
b1000 "
b1111001 +
b11100000000001001000110100 /
b1111010 1
1#
#160
0#
#170
b1001 *
b1111000 +
b100000000000001001000110100 /
b100100000000001001000110100 %
b1001 "
b1111001 1
1#
#180
0#
#190
b1010 *
b101000000000001001000110100 %
b1010 "
b1110111 +
b100100000000001001000110100 /
b1111000 1
1#
#200
0#
#210
b1011 *
b1110110 +
b101000000000001001000110100 /
b101100000000001001000110100 %
b1011 "
b1110111 1
1#
#220
0#
#230
b1100 *
b110000000000001001000110100 %
b1100 "
b1110101 +
b101100000000001001000110100 /
b1110110 1
1#
#240
0#
#250
b1101 *
b1110100 +
b110000000000001001000110100 /
b110100000000001001000110100 %
b1101 "
b1110101 1
1#
#260
0#
#270
b1110 *
b111000000000001001000110100 %
b1110 "
b1110011 +
b110100000000001001000110100 /
b1110100 1
1#
#280
0#
#290
b1111 *
b1110010 +
b111000000000001001000110100 /
b111100000000001001000110100 %
b1111 "
b1110011 1
1#
#300
0#
#310
b10000 *
b1000000000000001001000110100 %
b10000 "
b1110001 +
b111100000000001001000110100 /
b1110010 1
1#
#320
0#
#330
b10001 *
b1110000 +
b1000000000000001001000110100 /
b1000100000000001001000110100 %
b10001 "
b1110001 1
1#
#340
0#
#350
b10010 *
b1001000000000001001000110100 %
b10010 "
b1101111 +
b1000100000000001001000110100 /
b1110000 1
1#
#360
0#
#370
b10011 *
b1101110 +
b1001000000000001001000110100 /
b1001100000000001001000110100 %
b10011 "
b1101111 1
1#
#380
0#
#390
b10100 *
b1010000000000001001000110100 %
b10100 "
b1101101 +
b1001100000000001001000110100 /
b1101110 1
1#
#400
0#
#410
b10101 *
b1101100 +
b1010000000000001001000110100 /
b1010100000000001001000110100 %
b10101 "
b1101101 1
1#
#420
0#
#430
b10110 *
b1011000000000001001000110100 %
b10110 "
b1101011 +
b1010100000000001001000110100 /
b1101100 1
1#
#440
0#
#450
b10111 *
b1101010 +
b1011000000000001001000110100 /
b1011100000000001001000110100 %
b10111 "
b1101011 1
1#
#460
0#
#470
b11000 *
b1100000000000001001000110100 %
b11000 "
b1101001 +
b1011100000000001001000110100 /
b1101010 1
1#
#480
0#
#490
b11001 *
b1101000 +
b1100000000000001001000110100 /
b1100100000000001001000110100 %
b11001 "
b1101001 1
1#
#500
0#
#510
b11010 *
b1101000000000001001000110100 %
b11010 "
b1100111 +
b1100100000000001001000110100 /
b1101000 1
1#
#520
0#
#530
b11011 *
b1100110 +
b1101000000000001001000110100 /
b1101100000000001001000110100 %
b11011 "
b1100111 1
1#
#540
0#
#550
b11100 *
b1110000000000001001000110100 %
b11100 "
b1100101 +
b1101100000000001001000110100 /
b1100110 1
1#
#560
0#
#570
b11101 *
b1100100 +
b1110000000000001001000110100 /
b1110100000000001001000110100 %
b11101 "
b1100101 1
1#
#580
0#
#590
b11110 *
b1111000000000001001000110100 %
b11110 "
b1100011 +
b1110100000000001001000110100 /
b1100100 1
1#
#600
0#
#610
b11111 *
b1100010 +
b1111000000000001001000110100 /
b1111100000000001001000110100 %
b11111 "
b1100011 1
1#
#620
0#
#630
b100000 *
b10000000000000001001000110100 %
b100000 "
b1100001 +
b1111100000000001001000110100 /
b1100010 1
1#
#640
0#
#650
b100001 *
b1100000 +
b10000000000000001001000110100 /
b10000100000000001001000110100 %
b100001 "
b1100001 1
1#
#660
0#
#670
b100010 *
b10001000000000001001000110100 %
b100010 "
b1011111 +
b10000100000000001001000110100 /
b1100000 1
1#
#680
0#
#690
b100011 *
b1011110 +
b10001000000000001001000110100 /
b10001100000000001001000110100 %
b100011 "
b1011111 1
1#
#700
0#
#710
b100100 *
b10010000000000001001000110100 %
b100100 "
b1011101 +
b10001100000000001001000110100 /
b1011110 1
1#
#720
0#
#730
b100101 *
b1011100 +
b10010000000000001001000110100 /
b10010100000000001001000110100 %
b100101 "
b1011101 1
1#
#740
0#
#750
b100110 *
b10011000000000001001000110100 %
b100110 "
b1011011 +
b10010100000000001001000110100 /
b1011100 1
1#
#760
0#
#770
b100111 *
b1011010 +
b10011000000000001001000110100 /
b10011100000000001001000110100 %
b100111 "
b1011011 1
1#
#780
0#
#790
b101000 *
b10100000000000001001000110100 %
b101000 "
b1011001 +
b10011100000000001001000110100 /
b1011010 1
1#
#800
0#
#810
b101001 *
b1011000 +
b10100000000000001001000110100 /
b10100100000000001001000110100 %
b101001 "
b1011001 1
1#
#820
0#
#830
b101010 *
b10101000000000001001000110100 %
b101010 "
b1010111 +
b10100100000000001001000110100 /
b1011000 1
1#
#840
0#
#850
b101011 *
b1010110 +
b10101000000000001001000110100 /
b10101100000000001001000110100 %
b101011 "
b1010111 1
1#
#860
0#
#870
b101100 *
b10110000000000001001000110100 %
b101100 "
b1010101 +
b10101100000000001001000110100 /
b1010110 1
1#
#880
0#
#890
b101101 *
b1010100 +
b10110000000000001001000110100 /
b10110100000000001001000110100 %
b101101 "
b1010101 1
1#
#900
0#
#910
b101110 *
b10111000000000001001000110100 %
b101110 "
b1010011 +
b10110100000000001001000110100 /
b1010100 1
1#
#920
0#
#930
b101111 *
b1010010 +
b10111000000000001001000110100 /
b10111100000000001001000110100 %
b101111 "
b1010011 1
1#
#940
0#
#950
b110000 *
b11000000000000001001000110100 %
b110000 "
b1010001 +
b10111100000000001001000110100 /
b1010010 1
1#
#960
0#
#970
b110001 *
b1010000 +
b11000000000000001001000110100 /
b11000100000000001001000110100 %
b110001 "
b1010001 1
1#
#980
0#
#990
b110010 *
b11001000000000001001000110100 %
b110010 "
b1001111 +
b11000100000000001001000110100 /
b1010000 1
1#
#1000
0#
#1010
b110011 *
b1001110 +
b11001000000000001001000110100 /
b11001100000000001001000110100 %
b110011 "
b1001111 1
1#
#1020
0#
#1030
b110100 *
b11010000000000001001000110100 %
b110100 "
b1001101 +
b11001100000000001001000110100 /
b1001110 1
1#
#1040
0#
#1050
b110101 *
b1001100 +
b11010000000000001001000110100 /
b11010100000000001001000110100 %
b110101 "
b1001101 1
1#
#1060
0#
#1070
b110110 *
b11011000000000001001000110100 %
b110110 "
b1001011 +
b11010100000000001001000110100 /
b1001100 1
1#
#1080
0#
#1090
b110111 *
b1001010 +
b11011000000000001001000110100 /
b11011100000000001001000110100 %
b110111 "
b1001011 1
1#
#1100
0#
#1110
b111000 *
b11100000000000001001000110100 %
b111000 "
b1001001 +
b11011100000000001001000110100 /
b1001010 1
1#
#1120
0#
#1130
b111001 *
b1001000 +
b11100000000000001001000110100 /
b11100100000000001001000110100 %
b111001 "
b1001001 1
1#
#1140
0#
#1150
b111010 *
b11101000000000001001000110100 %
b111010 "
b1000111 +
b11100100000000001001000110100 /
b1001000 1
1#
#1160
0#
#1170
b111011 *
b1000110 +
b11101000000000001001000110100 /
b11101100000000001001000110100 %
b111011 "
b1000111 1
1#
#1180
0#
#1190
b111100 *
b11110000000000001001000110100 %
b111100 "
b1000101 +
b11101100000000001001000110100 /
b1000110 1
1#
#1200
0#
#1210
b111101 *
b1000100 +
b11110000000000001001000110100 /
b11110100000000001001000110100 %
b111101 "
b1000101 1
1#
#1220
0#
#1230
b111110 *
b11111000000000001001000110100 %
b111110 "
b1000011 +
b11110100000000001001000110100 /
b1000100 1
1#
#1240
0#
#1250
b111111 *
b1000010 +
b11111000000000001001000110100 /
b11111100000000001001000110100 %
b111111 "
b1000011 1
1#
#1260
0#
#1270
b1000000 *
b100000000000000001001000110100 %
b1000000 "
b1000001 +
b11111100000000001001000110100 /
b1000010 1
1#
#1280
0#
#1290
b1000001 *
b1000000 +
b100000000000000001001000110100 /
b100000100000000001001000110100 %
b1000001 "
b1000001 1
1#
#1300
0#
#1310
b1000010 *
b100001000000000001001000110100 %
b1000010 "
b111111 +
b100000100000000001001000110100 /
b1000000 1
1#
#1320
0#
#1330
b1000011 *
b111110 +
b100001000000000001001000110100 /
b100001100000000001001000110100 %
b1000011 "
b111111 1
1#
#1340
0#
#1350
b1000100 *
b100010000000000001001000110100 %
b1000100 "
b111101 +
b100001100000000001001000110100 /
b111110 1
1#
#1360
0#
#1370
b1000101 *
b111100 +
b100010000000000001001000110100 /
b100010100000000001001000110100 %
b1000101 "
b111101 1
1#
#1380
0#
#1390
b1000110 *
b100011000000000001001000110100 %
b1000110 "
b111011 +
b100010100000000001001000110100 /
b111100 1
1#
#1400
0#
#1410
b1000111 *
b111010 +
b100011000000000001001000110100 /
b100011100000000001001000110100 %
b1000111 "
b111011 1
1#
#1420
0#
#1430
b1001000 *
b100100000000000001001000110100 %
b1001000 "
b111001 +
b100011100000000001001000110100 /
b111010 1
1#
#1440
0#
#1450
b1001001 *
b111000 +
b100100000000000001001000110100 /
b100100100000000001001000110100 %
b1001001 "
b111001 1
1#
#1460
0#
#1470
b1001010 *
b100101000000000001001000110100 %
b1001010 "
b110111 +
b100100100000000001001000110100 /
b111000 1
1#
#1480
0#
#1490
b1001011 *
b110110 +
b100101000000000001001000110100 /
b100101100000000001001000110100 %
b1001011 "
b110111 1
1#
#1500
0#
#1510
b1001100 *
b100110000000000001001000110100 %
b1001100 "
b110101 +
b100101100000000001001000110100 /
b110110 1
1#
#1520
0#
#1530
b1001101 *
b110100 +
b100110000000000001001000110100 /
b100110100000000001001000110100 %
b1001101 "
b110101 1
1#
#1540
0#
#1550
b1001110 *
b100111000000000001001000110100 %
b1001110 "
b110011 +
b100110100000000001001000110100 /
b110100 1
1#
#1560
0#
#1570
b1001111 *
b110010 +
b100111000000000001001000110100 /
b100111100000000001001000110100 %
b1001111 "
b110011 1
1#
#1580
0#
#1590
b1010000 *
b101000000000000001001000110100 %
b1010000 "
b110001 +
b100111100000000001001000110100 /
b110010 1
1#
#1600
0#
#1610
b1010001 *
b110000 +
b101000000000000001001000110100 /
b101000100000000001001000110100 %
b1010001 "
b110001 1
1#
#1620
0#
#1630
b1010010 *
b101001000000000001001000110100 %
b1010010 "
b101111 +
b101000100000000001001000110100 /
b110000 1
1#
#1640
0#
#1650
b1010011 *
b101110 +
b101001000000000001001000110100 /
b101001100000000001001000110100 %
b1010011 "
b101111 1
1#
#1660
0#
#1670
b1010100 *
b101010000000000001001000110100 %
b1010100 "
b101101 +
b101001100000000001001000110100 /
b101110 1
1#
#1680
0#
#1690
b1010101 *
b101100 +
b101010000000000001001000110100 /
b101010100000000001001000110100 %
b1010101 "
b101101 1
1#
#1700
0#
#1710
b1010110 *
b101011000000000001001000110100 %
b1010110 "
b101011 +
b101010100000000001001000110100 /
b101100 1
1#
#1720
0#
#1730
b1010111 *
b101010 +
b101011000000000001001000110100 /
b101011100000000001001000110100 %
b1010111 "
b101011 1
1#
#1740
0#
#1750
b1011000 *
b101100000000000001001000110100 %
b1011000 "
b101001 +
b101011100000000001001000110100 /
b101010 1
1#
#1760
0#
#1770
b1011001 *
b101000 +
b101100000000000001001000110100 /
b101100100000000001001000110100 %
b1011001 "
b101001 1
1#
#1780
0#
#1790
b1011010 *
b101101000000000001001000110100 %
b1011010 "
b100111 +
b101100100000000001001000110100 /
b101000 1
1#
#1800
0#
#1810
b1011011 *
b100110 +
b101101000000000001001000110100 /
b101101100000000001001000110100 %
b1011011 "
b100111 1
1#
#1820
0#
#1830
b1011100 *
b101110000000000001001000110100 %
b1011100 "
b100101 +
b101101100000000001001000110100 /
b100110 1
1#
#1840
0#
#1850
b1011101 *
b100100 +
b101110000000000001001000110100 /
b101110100000000001001000110100 %
b1011101 "
b100101 1
1#
#1860
0#
#1870
b1011110 *
b101111000000000001001000110100 %
b1011110 "
b100011 +
b101110100000000001001000110100 /
b100100 1
1#
#1880
0#
#1890
b1011111 *
b100010 +
b101111000000000001001000110100 /
b101111100000000001001000110100 %
b1011111 "
b100011 1
1#
#1900
0#
#1910
b1100000 *
b110000000000000001001000110100 %
b1100000 "
b100001 +
b101111100000000001001000110100 /
b100010 1
1#
#1920
0#
#1930
b1100001 *
b100000 +
b110000000000000001001000110100 /
b110000100000000001001000110100 %
b1100001 "
b100001 1
1#
#1940
0#
#1950
b1100010 *
b110001000000000001001000110100 %
b1100010 "
b11111 +
b110000100000000001001000110100 /
b100000 1
1#
#1960
0#
#1970
b1100011 *
b11110 +
b110001000000000001001000110100 /
b110001100000000001001000110100 %
b1100011 "
b11111 1
1#
#1980
0#
#1990
b1100100 *
b110010000000000001001000110100 %
b1100100 "
b11101 +
b110001100000000001001000110100 /
b11110 1
1#
#2000
0#
#2010
b1100101 *
b11100 +
b110010000000000001001000110100 /
b110010100000000001001000110100 %
b1100101 "
b11101 1
1#
#2020
0#
#2030
b1100110 *
b110011000000000001001000110100 %
b1100110 "
b11011 +
b110010100000000001001000110100 /
b11100 1
1#
#2040
0#
#2050
b1100111 *
b11010 +
b110011000000000001001000110100 /
b110011100000000001001000110100 %
b1100111 "
b11011 1
1#
#2060
0#
#2070
b1101000 *
b110100000000000001001000110100 %
b1101000 "
b11001 +
b110011100000000001001000110100 /
b11010 1
1#
#2080
0#
#2090
b1101001 *
b11000 +
b110100000000000001001000110100 /
b110100100000000001001000110100 %
b1101001 "
b11001 1
1#
#2100
0#
#2110
b1101010 *
b110101000000000001001000110100 %
b1101010 "
b10111 +
b110100100000000001001000110100 /
b11000 1
1#
#2120
0#
#2130
b1101011 *
b1 0
b10110 +
b110101000000000001001000110100 /
b110101100000000001001000110100 %
b1101011 "
b1 3
b10111 1
1#
#2140
0#
#2150
b1101100 *
b110110000000000001001000110100 %
b1101100 "
b1000000000001000000000001 ,
b10 0
b10101 +
b110101100000000001001000110100 /
b10 3
b10110 1
1#
#2160
0#
#2170
b1101101 *
b1000000000001000000000010 ,
b100 0
b10100 +
b110110000000000001001000110100 /
b110110100000000001001000110100 %
b1101101 "
b100 3
b10101 1
1#
#2180
0#
#2190
b1101110 *
b110111000000000001001000110100 %
b1101110 "
b1000000000001000000000100 ,
b1000 0
b10011 +
b110110100000000001001000110100 /
b1000 3
b10100 1
1#
#2200
0#
#2210
b1101111 *
b1000000000001000000001000 ,
b10000 0
b10010 +
b110111000000000001001000110100 /
b110111100000000001001000110100 %
b1101111 "
b10000 3
b10011 1
1#
#2220
0#
#2230
b1110000 *
b111000000000000001001000110100 %
b1110000 "
b1000000000001000000010000 ,
b100000 0
b10001 +
b110111100000000001001000110100 /
b100000 3
b10010 1
1#
#2240
0#
#2250
b1110001 *
b1000000000001000000100000 ,
b1000000 0
b10000 +
b111000000000000001001000110100 /
b111000100000000001001000110100 %
b1110001 "
b1000000 3
b10001 1
1#
#2260
0#
#2270
b1110010 *
b111001000000000001001000110100 %
b1110010 "
b1000000000001000001000000 ,
b10000000 0
b1111 +
b111000100000000001001000110100 /
b10000000 3
b10000 1
1#
#2280
0#
#2290
b1110011 *
b1000000000001000010000000 ,
b100000000 0
b1110 +
b111001000000000001001000110100 /
b111001100000000001001000110100 %
b1110011 "
b100000000 3
b1111 1
1#
#2300
0#
#2310
b1110100 *
b111010000000000001001000110100 %
b1110100 "
b1000000000001000100000000 ,
b1000000000 0
b1101 +
b111001100000000001001000110100 /
b1000000000 3
b1110 1
1#
#2320
0#
#2330
b1110101 *
b1000000000001001000000000 ,
b10000000000 0
b1100 +
b111010000000000001001000110100 /
b111010100000000001001000110100 %
b1110101 "
b10000000000 3
b1101 1
1#
#2340
0#
#2350
b1110110 *
b111011000000000001001000110100 %
b1110110 "
b1000000000001010000000000 ,
b100000000001 0
b1011 +
b111010100000000001001000110100 /
b100000000001 3
b1100 1
1#
#2360
0#
#2370
b1110111 *
b1000000000001100000000001 ,
b1000000000010 0
b1010 +
b111011000000000001001000110100 /
b111011100000000001001000110100 %
b1110111 "
b1000000000010 3
b1011 1
1#
#2380
0#
#2390
b1111000 *
b111100000000000001001000110100 %
b1111000 "
b1000000000010000000000010 ,
b10000000000100 0
b1001 +
b111011100000000001001000110100 /
b10000000000100 3
b1010 1
1#
#2400
0#
#2410
b1111001 *
b1000000000011000000000100 ,
b100000000001001 0
b1000 +
b111100000000000001001000110100 /
b111100100000000001001000110100 %
b1111001 "
b100000000001001 3
b1001 1
1#
#2420
0#
#2430
b1111010 *
b111101000000000001001000110100 %
b1111010 "
b1000000000101000000001001 ,
b1000000000010010 0
b111 +
b111100100000000001001000110100 /
b1000000000010010 3
b1000 1
1#
#2440
0#
#2450
b1111011 *
b1000000001001000000010010 ,
b10000000000100100 0
b110 +
b111101000000000001001000110100 /
b111101100000000001001000110100 %
b1111011 "
b10000000000100100 3
b111 1
1#
#2460
0#
#2470
b1111100 *
b111110000000000001001000110100 %
b1111100 "
b1000000010001000000100100 ,
b100000000001001000 0
b101 +
b111101100000000001001000110100 /
b100000000001001000 3
b110 1
1#
#2480
0#
#2490
b1111101 *
b1000000100001000001001000 ,
b1000000000010010001 0
b100 +
b111110000000000001001000110100 /
b111110100000000001001000110100 %
b1111101 "
b1000000000010010001 3
b101 1
1#
#2500
0#
#2510
b1111110 *
b111111000000000001001000110100 %
b1111110 "
b1000001000001000010010001 ,
b10000000000100100011 0
b11 +
b111110100000000001001000110100 /
b10000000000100100011 3
b100 1
1#
#2520
0#
#2530
b1111111 *
b1000010000001000100100011 ,
b100000000001001000110 0
b10 +
b111111000000000001001000110100 /
b111111100000000001001000110100 %
b1111111 "
b100000000001001000110 3
b11 1
1#
#2540
0#
#2550
b10000000 *
b1000000000000000001001000110100 %
b10000000 "
b1000100000001001001000110 ,
b1000000000010010001101 0
b1 +
b111111100000000001000000000000 /
b111111100000000001001000110100 -
b1000000000010010001101 3
b10 1
1#
#2560
0#
#2570
b10000001 *
b1001000000001010010001101 ,
b10000000000100000000000 0
b1000000000001001000110100 .
b0 +
b1000000000000000001001000110100 -
b1000000100000000001001000110100 %
b10000001 "
b10000000000100000000000 3
b100000000001000000000000 2
b1 1
1#
#2580
0#
#2590
b10000010 *
b1000001000000000001001000110100 %
b10000010 "
b1010000000001101000110100 ,
b100000000001000000000000 0
b1 +
b1000000100000000001001000110100 -
b100000000001000000000000 3
b0 1
1#
#2600
0#
#2610
b10000011 *
b1100000000010001000110100 ,
b10000000000100000000000 0
b10 +
b1000001000000000001001000110100 -
b1000001100000000001001000110100 %
b10000011 "
b10000000000100000000000 3
b1 1
1#
#2620
0#
#2630
b10000100 *
b1000010000000000001001000110100 %
b10000100 "
b1010000000001101000110100 ,
b1000000000010000000000 0
b11 +
b1000001100000000001001000110100 -
b1000000000010000000000 3
b10 1
1#
#2640
0#
#2650
b10000101 *
b1001000000001011000110100 ,
b100000000001000000000 0
b100 +
b1000010000000000001001000110100 -
b1000010100000000001001000110100 %
b10000101 "
b100000000001000000000 3
b11 1
1#
#2660
0#
#2670
b10000110 *
b1000011000000000001001000110100 %
b10000110 "
b1000100000001010000110100 ,
b10000000000100000000 0
b101 +
b1000010100000000001001000110100 -
b10000000000100000000 3
b100 1
1#
#2680
0#
#2690
b10000111 *
b1000010000001001100110100 ,
b1000000000010000000 0
b110 +
b1000011000000000001001000110100 -
b1000011100000000001001000110100 %
b10000111 "
b1000000000010000000 3
b101 1
1#
#2700
0#
#2710
b10001000 *
b1000100000000000001001000110100 %
b10001000 "
b1000001000001001010110100 ,
b100000000001000000 0
b111 +
b1000011100000000001001000110100 -
b100000000001000000 3
b110 1
1#
#2720
0#
#2730
b10001001 *
b1000000100001001001110100 ,
b10000000000100000 0
b1000 +
b1000100000000000001001000110100 -
b1000100100000000001001000110100 %
b10001001 "
b10000000000100000 3
b111 1
1#
#2740
0#
#2750
b10001010 *
b1000101000000000001001000110100 %
b10001010 "
b1000000010001001001010100 ,
b1000000000010000 0
b1001 +
b1000100100000000001001000110100 -
b1000000000010000 3
b1000 1
1#
#2760
0#
#2770
b10001011 *
b1000000001001001001000100 ,
b100000000001000 0
b1010 +
b1000101000000000001001000110100 -
b1000101100000000001001000110100 %
b10001011 "
b100000000001000 3
b1001 1
1#
#2780
0#
#2790
b10001100 *
b1000110000000000001001000110100 %
b10001100 "
b1000000000101001000111100 ,
b10000000000100 0
b1011 +
b1000101100000000001001000110100 -
b10000000000100 3
b1010 1
1#
#2800
0#
#2810
b10001101 *
b1000000000011001000111000 ,
b1000000000010 0
b1100 +
b1000110000000000001001000110100 -
b1000110100000000001001000110100 %
b10001101 "
b1000000000010 3
b1011 1
1#
#2820
0#
#2830
b10001110 *
b1000111000000000001001000110100 %
b10001110 "
b1000000000010001000110110 ,
b100000000001 0
b1101 +
b1000110100000000001001000110100 -
b100000000001 3
b1100 1
1#
#2840
0#
#2850
b10001111 *
b1000000000001101000110101 ,
b10000000000 0
b1110 +
b1000111000000000001001000110100 -
b1000111100000000001001000110100 %
b10001111 "
b10000000000 3
b1101 1
1#
#2860
0#
#2870
b10010000 *
b1001000000000000001001000110100 %
b10010000 "
b1000000000001011000110100 ,
b1000000000 0
b1111 +
b1000111100000000001001000110100 -
b1000000000 3
b1110 1
1#
#2880
0#
#2890
b10010001 *
b1000000000001010000110100 ,
b100000000 0
b10000 +
b1001000000000000001001000110100 -
b1001000100000000001001000110100 %
b10010001 "
b100000000 3
b1111 1
1#
#2900
0#
#2910
b10010010 *
b1001001000000000001001000110100 %
b10010010 "
b1000000000001001100110100 ,
b10000000 0
b10001 +
b1001000100000000001001000110100 -
b10000000 3
b10000 1
1#
#2920
0#
#2930
b10010011 *
b1000000000001001010110100 ,
b1000000 0
b10010 +
b1001001000000000001001000110100 -
b1001001100000000001001000110100 %
b10010011 "
b1000000 3
b10001 1
1#
#2940
0#
#2950
b10010100 *
b1001010000000000001001000110100 %
b10010100 "
b1000000000001001001110100 ,
b100000 0
b10011 +
b1001001100000000001001000110100 -
b100000 3
b10010 1
1#
#2960
0#
#2970
b10010101 *
b1000000000001001001010100 ,
b10000 0
b10100 +
b1001010000000000001001000110100 -
b1001010100000000001001000110100 %
b10010101 "
b10000 3
b10011 1
1#
#2980
0#
#2990
b10010110 *
b1001011000000000001001000110100 %
b10010110 "
b1000000000001001001000100 ,
b1000 0
b10101 +
b1001010100000000001001000110100 -
b1000 3
b10100 1
1#
#3000
0#
#3010
b10010111 *
b1000000000001001000111100 ,
b100 0
b10110 +
b1001011000000000001001000110100 -
b1001011100000000001001000110100 %
b10010111 "
b100 3
b10101 1
1#
#3020
0#
#3030
b10011000 *
b1001100000000000001001000110100 %
b10011000 "
b1000000000001001000111000 ,
b10 0
b10111 +
b1001011100000000001001000110100 -
b10 3
b10110 1
1#
#3040
0#
#3050
b10011001 *
b1000000000001001000110110 ,
b1 0
b11000 +
b1001100000000000001001000110100 -
b1001100100000000001001000110100 %
b10011001 "
b1 3
b10111 1
1#
#3060
0#
#3070
b10011010 *
b1001101000000000001001000110100 %
b10011010 "
b1000000000001001000110101 ,
b0 0
b11001 +
b1001100100000000001001000110100 -
b0 3
b11000 1
1#
#3080
0#
#3090
b10011011 *
b1000000000001001000110100 ,
b11010 +
b1001101000000000001001000110100 -
b1001101100000000001001000110100 %
b10011011 "
b11001 1
1#
#3100
0#
#3110
b10011100 *
b1001110000000000001001000110100 %
b10011100 "
b11011 +
b1001101100000000001001000110100 -
b11010 1
1#
#3120
0#
#3130
b10011101 *
b11100 +
b1001110000000000001001000110100 -
b1001110100000000001001000110100 %
b10011101 "
b11011 1
1#
#3140
0#
#3150
b10011110 *
b1001111000000000001001000110100 %
b10011110 "
b11101 +
b1001110100000000001001000110100 -
b11100 1
1#
#3160
0#
#3170
b10011111 *
b11110 +
b1001111000000000001001000110100 -
b1001111100000000001001000110100 %
b10011111 "
b11101 1
1#
#3180
0#
#3190
b10100000 *
b1010000000000000001001000110100 %
b10100000 "
b11111 +
b1001111100000000001001000110100 -
b11110 1
1#
#3200
0#
#3210
b10100001 *
b100000 +
b1010000000000000001001000110100 -
b1010000100000000001001000110100 %
b10100001 "
b11111 1
1#
#3220
0#
#3230
b10100010 *
b1010001000000000001001000110100 %
b10100010 "
b100001 +
b1010000100000000001001000110100 -
b100000 1
1#
#3240
0#
#3250
b10100011 *
b100010 +
b1010001000000000001001000110100 -
b1010001100000000001001000110100 %
b10100011 "
b100001 1
1#
#3260
0#
#3270
b10100100 *
b1010010000000000001001000110100 %
b10100100 "
b100011 +
b1010001100000000001001000110100 -
b100010 1
1#
#3280
0#
#3290
b10100101 *
b100100 +
b1010010000000000001001000110100 -
b1010010100000000001001000110100 %
b10100101 "
b100011 1
1#
#3300
0#
#3310
b10100110 *
b1010011000000000001001000110100 %
b10100110 "
b100101 +
b1010010100000000001001000110100 -
b100100 1
1#
#3320
0#
#3330
b10100111 *
b100110 +
b1010011000000000001001000110100 -
b1010011100000000001001000110100 %
b10100111 "
b100101 1
1#
#3340
0#
