leadingzero.sv
module lz(
	input wire clk,
	input wire [23:0] v,

	output wire [4:0] num
);

 reg [4:0] cnum;
 assign num = cnum;

always @(posedge clk) begin
	if (v[23]) cnum <= 5'd0;
	else if (v[22]) cnum <= 5'd1;
	else if (v[21]) cnum <= 5'd2;
	else if (v[20]) cnum <= 5'd3;
	else if (v[19]) cnum <= 5'd4;
	else if (v[18]) cnum <= 5'd5;
	else if (v[17]) cnum <= 5'd6;
	else if (v[16]) cnum <= 5'd7;
	else if (v[15]) cnum <= 5'd8;
	else if (v[14]) cnum <= 5'd9;
	else if (v[13]) cnum <= 5'd10;
	else if (v[12]) cnum <= 5'd11;
	else if (v[11]) cnum <= 5'd12;
	else if (v[10]) cnum <= 5'd13;
	else if (v[ 9]) cnum <= 5'd14;
	else if (v[ 8]) cnum <= 5'd15;
	else if (v[ 7]) cnum <= 5'd16;
	else if (v[ 6]) cnum <= 5'd17;
	else if (v[ 5]) cnum <= 5'd18;
	else if (v[ 4]) cnum <= 5'd19;
	else if (v[ 3]) cnum <= 5'd20;
	else if (v[ 2]) cnum <= 5'd21;
	else if (v[ 1]) cnum <= 5'd22;
	else if (v[ 0]) cnum <= 5'd23;
	else cnum <= 5'd31;
end

endmodule

module lzv(
	input wire clk,
	input wire [23:0] v,

	output wire [23:0] res
);

 reg [23:0] cnum;
 assign res = cnum;

always @(posedge clk) begin
	if (v[23]) cnum <= v;
	else if (v[22]) cnum <= {v[22:0],  1'b0};
	else if (v[21]) cnum <= {v[21:0],  2'b0};
	else if (v[20]) cnum <= {v[20:0],  3'b0};
	else if (v[19]) cnum <= {v[19:0],  4'b0};
	else if (v[18]) cnum <= {v[18:0],  5'b0};
	else if (v[17]) cnum <= {v[17:0],  6'b0};
	else if (v[16]) cnum <= {v[16:0],  7'b0};
	else if (v[15]) cnum <= {v[15:0],  8'b0};
	else if (v[14]) cnum <= {v[14:0],  9'b0};
	else if (v[13]) cnum <= {v[13:0], 10'b0};
	else if (v[12]) cnum <= {v[12:0], 11'b0};
	else if (v[11]) cnum <= {v[11:0], 12'b0};
	else if (v[10]) cnum <= {v[10:0], 13'b0};
	else if (v[ 9]) cnum <= {v[ 9:0], 14'b0};
	else if (v[ 8]) cnum <= {v[ 8:0], 15'b0};
	else if (v[ 7]) cnum <= {v[ 7:0], 16'b0};
	else if (v[ 6]) cnum <= {v[ 6:0], 17'b0};
	else if (v[ 5]) cnum <= {v[ 5:0], 18'b0};
	else if (v[ 4]) cnum <= {v[ 4:0], 19'b0};
	else if (v[ 3]) cnum <= {v[ 3:0], 20'b0};
	else if (v[ 2]) cnum <= {v[ 2:0], 21'b0};
	else if (v[ 1]) cnum <= {v[ 1:0], 22'b0};
	else cnum <=24'h800_000;
end

endmodule

lzsim.v
`timescale 1ps/1ps
module lzsim();

  reg clk;
  wire[23:0] res;
  reg [23:0] acnt;

	always @(posedge clk) begin
		acnt <= acnt + 24'b1;
	end

	lzv lzm(
		.clk(clk),
		.v(acnt),
		.res(res)
	);

  initial begin
    clk = 0;
		acnt <= 8'b0;
    forever #10 clk = ~clk;
  end

 integer i;  
  initial begin
    $dumpfile("lzsim.vcd");
    $dumpvars(0, lzsim);
//    for(i = 0;i < 2**FIFO_DEPTH;i++)
//      $dumpvars(1,u0.data[i]);
    $monitor ("%t: clk = %b", $time, clk);
  end

  initial begin
    #5000 $finish();
  end

endmodule

lzsim.vcd
$date
	Thu Apr 23 19:52:40 2020
$end
$version
	Icarus Verilog
$end
$timescale
	1ps
$end
$scope module lzsim $end
$var wire 24 ! res [23:0] $end
$var reg 24 " acnt [23:0] $end
$var reg 1 # clk $end
$scope module lzm $end
$var wire 1 # clk $end
$var wire 24 $ res [23:0] $end
$var wire 24 % v [23:0] $end
$var reg 24 & cnum [23:0] $end
$upscope $end
$upscope $end
$enddefinitions $end
#0
$dumpvars
bx &
b0 %
bx $
0#
b0 "
bx !
$end
#10
b100000000000000000000000 !
b100000000000000000000000 $
b100000000000000000000000 &
b1 "
b1 %
1#
#20
0#
#30
b10 "
b10 %
1#
#40
0#
#50
b11 "
b11 %
1#
#60
0#
#70
b100 "
b100 %
b110000000000000000000000 !
b110000000000000000000000 $
b110000000000000000000000 &
1#
#80
0#
#90
b100000000000000000000000 !
b100000000000000000000000 $
b100000000000000000000000 &
b101 "
b101 %
1#
#100
0#
#110
b110 "
b110 %
b101000000000000000000000 !
b101000000000000000000000 $
b101000000000000000000000 &
1#
#120
0#
#130
b110000000000000000000000 !
b110000000000000000000000 $
b110000000000000000000000 &
b111 "
b111 %
1#
#140
0#
#150
b1000 "
b1000 %
b111000000000000000000000 !
b111000000000000000000000 $
b111000000000000000000000 &
1#
#160
0#
#170
b100000000000000000000000 !
b100000000000000000000000 $
b100000000000000000000000 &
b1001 "
b1001 %
1#
#180
0#
#190
b1010 "
b1010 %
b100100000000000000000000 !
b100100000000000000000000 $
b100100000000000000000000 &
1#
#200
0#
#210
b101000000000000000000000 !
b101000000000000000000000 $
b101000000000000000000000 &
b1011 "
b1011 %
1#
#220
0#
#230
b1100 "
b1100 %
b101100000000000000000000 !
b101100000000000000000000 $
b101100000000000000000000 &
1#
#240
0#
#250
b110000000000000000000000 !
b110000000000000000000000 $
b110000000000000000000000 &
b1101 "
b1101 %
1#
#260
0#
#270
b1110 "
b1110 %
b110100000000000000000000 !
b110100000000000000000000 $
b110100000000000000000000 &
1#
#280
0#
#290
b111000000000000000000000 !
b111000000000000000000000 $
b111000000000000000000000 &
b1111 "
b1111 %
1#
#300
0#
#310
b10000 "
b10000 %
b111100000000000000000000 !
b111100000000000000000000 $
b111100000000000000000000 &
1#
#320
0#
#330
b100000000000000000000000 !
b100000000000000000000000 $
b100000000000000000000000 &
b10001 "
b10001 %
1#
#340
0#
#350
b10010 "
b10010 %
b100010000000000000000000 !
b100010000000000000000000 $
b100010000000000000000000 &
1#
#360
0#
#370
b100100000000000000000000 !
b100100000000000000000000 $
b100100000000000000000000 &
b10011 "
b10011 %
1#
#380
0#
#390
b10100 "
b10100 %
b100110000000000000000000 !
b100110000000000000000000 $
b100110000000000000000000 &
1#
#400
0#
#410
b101000000000000000000000 !
b101000000000000000000000 $
b101000000000000000000000 &
b10101 "
b10101 %
1#
#420
0#
#430
b10110 "
b10110 %
b101010000000000000000000 !
b101010000000000000000000 $
b101010000000000000000000 &
1#
#440
0#
#450
b101100000000000000000000 !
b101100000000000000000000 $
b101100000000000000000000 &
b10111 "
b10111 %
1#
#460
0#
#470
b11000 "
b11000 %
b101110000000000000000000 !
b101110000000000000000000 $
b101110000000000000000000 &
1#
#480
0#
#490
b110000000000000000000000 !
b110000000000000000000000 $
b110000000000000000000000 &
b11001 "
b11001 %
1#
#500
0#
#510
b11010 "
b11010 %
b110010000000000000000000 !
b110010000000000000000000 $
b110010000000000000000000 &
1#
#520
0#
#530
b110100000000000000000000 !
b110100000000000000000000 $
b110100000000000000000000 &
b11011 "
b11011 %
1#
#540
0#
#550
b11100 "
b11100 %
b110110000000000000000000 !
b110110000000000000000000 $
b110110000000000000000000 &
1#
#560
0#
#570
b111000000000000000000000 !
b111000000000000000000000 $
b111000000000000000000000 &
b11101 "
b11101 %
1#
#580
0#
#590
b11110 "
b11110 %
b111010000000000000000000 !
b111010000000000000000000 $
b111010000000000000000000 &
1#
#600
0#
#610
b111100000000000000000000 !
b111100000000000000000000 $
b111100000000000000000000 &
b11111 "
b11111 %
1#
#620
0#
#630
b100000 "
b100000 %
b111110000000000000000000 !
b111110000000000000000000 $
b111110000000000000000000 &
1#
#640
0#
#650
b100000000000000000000000 !
b100000000000000000000000 $
b100000000000000000000000 &
b100001 "
b100001 %
1#
#660
0#
#670
b100010 "
b100010 %
b100001000000000000000000 !
b100001000000000000000000 $
b100001000000000000000000 &
1#
#680
0#
#690
b100010000000000000000000 !
b100010000000000000000000 $
b100010000000000000000000 &
b100011 "
b100011 %
1#
#700
0#
#710
b100100 "
b100100 %
b100011000000000000000000 !
b100011000000000000000000 $
b100011000000000000000000 &
1#
#720
0#
#730
b100100000000000000000000 !
b100100000000000000000000 $
b100100000000000000000000 &
b100101 "
b100101 %
1#
#740
0#
#750
b100110 "
b100110 %
b100101000000000000000000 !
b100101000000000000000000 $
b100101000000000000000000 &
1#
#760
0#
#770
b100110000000000000000000 !
b100110000000000000000000 $
b100110000000000000000000 &
b100111 "
b100111 %
1#
#780
0#
#790
b101000 "
b101000 %
b100111000000000000000000 !
b100111000000000000000000 $
b100111000000000000000000 &
1#
#800
0#
#810
b101000000000000000000000 !
b101000000000000000000000 $
b101000000000000000000000 &
b101001 "
b101001 %
1#
#820
0#
#830
b101010 "
b101010 %
b101001000000000000000000 !
b101001000000000000000000 $
b101001000000000000000000 &
1#
#840
0#
#850
b101010000000000000000000 !
b101010000000000000000000 $
b101010000000000000000000 &
b101011 "
b101011 %
1#
#860
0#
#870
b101100 "
b101100 %
b101011000000000000000000 !
b101011000000000000000000 $
b101011000000000000000000 &
1#
#880
0#
#890
b101100000000000000000000 !
b101100000000000000000000 $
b101100000000000000000000 &
b101101 "
b101101 %
1#
#900
0#
#910
b101110 "
b101110 %
b101101000000000000000000 !
b101101000000000000000000 $
b101101000000000000000000 &
1#
#920
0#
#930
b101110000000000000000000 !
b101110000000000000000000 $
b101110000000000000000000 &
b101111 "
b101111 %
1#
#940
0#
#950
b110000 "
b110000 %
b101111000000000000000000 !
b101111000000000000000000 $
b101111000000000000000000 &
1#
#960
0#
#970
b110000000000000000000000 !
b110000000000000000000000 $
b110000000000000000000000 &
b110001 "
b110001 %
1#
#980
0#
#990
b110010 "
b110010 %
b110001000000000000000000 !
b110001000000000000000000 $
b110001000000000000000000 &
1#
#1000
0#
#1010
b110010000000000000000000 !
b110010000000000000000000 $
b110010000000000000000000 &
b110011 "
b110011 %
1#
#1020
0#
#1030
b110100 "
b110100 %
b110011000000000000000000 !
b110011000000000000000000 $
b110011000000000000000000 &
1#
#1040
0#
#1050
b110100000000000000000000 !
b110100000000000000000000 $
b110100000000000000000000 &
b110101 "
b110101 %
1#
#1060
0#
#1070
b110110 "
b110110 %
b110101000000000000000000 !
b110101000000000000000000 $
b110101000000000000000000 &
1#
#1080
0#
#1090
b110110000000000000000000 !
b110110000000000000000000 $
b110110000000000000000000 &
b110111 "
b110111 %
1#
#1100
0#
#1110
b111000 "
b111000 %
b110111000000000000000000 !
b110111000000000000000000 $
b110111000000000000000000 &
1#
#1120
0#
#1130
b111000000000000000000000 !
b111000000000000000000000 $
b111000000000000000000000 &
b111001 "
b111001 %
1#
#1140
0#
#1150
b111010 "
b111010 %
b111001000000000000000000 !
b111001000000000000000000 $
b111001000000000000000000 &
1#
#1160
0#
#1170
b111010000000000000000000 !
b111010000000000000000000 $
b111010000000000000000000 &
b111011 "
b111011 %
1#
#1180
0#
#1190
b111100 "
b111100 %
b111011000000000000000000 !
b111011000000000000000000 $
b111011000000000000000000 &
1#
#1200
0#
#1210
b111100000000000000000000 !
b111100000000000000000000 $
b111100000000000000000000 &
b111101 "
b111101 %
1#
#1220
0#
#1230
b111110 "
b111110 %
b111101000000000000000000 !
b111101000000000000000000 $
b111101000000000000000000 &
1#
#1240
0#
#1250
b111110000000000000000000 !
b111110000000000000000000 $
b111110000000000000000000 &
b111111 "
b111111 %
1#
#1260
0#
#1270
b1000000 "
b1000000 %
b111111000000000000000000 !
b111111000000000000000000 $
b111111000000000000000000 &
1#
#1280
0#
#1290
b100000000000000000000000 !
b100000000000000000000000 $
b100000000000000000000000 &
b1000001 "
b1000001 %
1#
#1300
0#
#1310
b1000010 "
b1000010 %
b100000100000000000000000 !
b100000100000000000000000 $
b100000100000000000000000 &
1#
#1320
0#
#1330
b100001000000000000000000 !
b100001000000000000000000 $
b100001000000000000000000 &
b1000011 "
b1000011 %
1#
#1340
0#
#1350
b1000100 "
b1000100 %
b100001100000000000000000 !
b100001100000000000000000 $
b100001100000000000000000 &
1#
#1360
0#
#1370
b100010000000000000000000 !
b100010000000000000000000 $
b100010000000000000000000 &
b1000101 "
b1000101 %
1#
#1380
0#
#1390
b1000110 "
b1000110 %
b100010100000000000000000 !
b100010100000000000000000 $
b100010100000000000000000 &
1#
#1400
0#
#1410
b100011000000000000000000 !
b100011000000000000000000 $
b100011000000000000000000 &
b1000111 "
b1000111 %
1#
#1420
0#
#1430
b1001000 "
b1001000 %
b100011100000000000000000 !
b100011100000000000000000 $
b100011100000000000000000 &
1#
#1440
0#
#1450
b100100000000000000000000 !
b100100000000000000000000 $
b100100000000000000000000 &
b1001001 "
b1001001 %
1#
#1460
0#
#1470
b1001010 "
b1001010 %
b100100100000000000000000 !
b100100100000000000000000 $
b100100100000000000000000 &
1#
#1480
0#
#1490
b100101000000000000000000 !
b100101000000000000000000 $
b100101000000000000000000 &
b1001011 "
b1001011 %
1#
#1500
0#
#1510
b1001100 "
b1001100 %
b100101100000000000000000 !
b100101100000000000000000 $
b100101100000000000000000 &
1#
#1520
0#
#1530
b100110000000000000000000 !
b100110000000000000000000 $
b100110000000000000000000 &
b1001101 "
b1001101 %
1#
#1540
0#
#1550
b1001110 "
b1001110 %
b100110100000000000000000 !
b100110100000000000000000 $
b100110100000000000000000 &
1#
#1560
0#
#1570
b100111000000000000000000 !
b100111000000000000000000 $
b100111000000000000000000 &
b1001111 "
b1001111 %
1#
#1580
0#
#1590
b1010000 "
b1010000 %
b100111100000000000000000 !
b100111100000000000000000 $
b100111100000000000000000 &
1#
#1600
0#
#1610
b101000000000000000000000 !
b101000000000000000000000 $
b101000000000000000000000 &
b1010001 "
b1010001 %
1#
#1620
0#
#1630
b1010010 "
b1010010 %
b101000100000000000000000 !
b101000100000000000000000 $
b101000100000000000000000 &
1#
#1640
0#
#1650
b101001000000000000000000 !
b101001000000000000000000 $
b101001000000000000000000 &
b1010011 "
b1010011 %
1#
#1660
0#
#1670
b1010100 "
b1010100 %
b101001100000000000000000 !
b101001100000000000000000 $
b101001100000000000000000 &
1#
#1680
0#
#1690
b101010000000000000000000 !
b101010000000000000000000 $
b101010000000000000000000 &
b1010101 "
b1010101 %
1#
#1700
0#
#1710
b1010110 "
b1010110 %
b101010100000000000000000 !
b101010100000000000000000 $
b101010100000000000000000 &
1#
#1720
0#
#1730
b101011000000000000000000 !
b101011000000000000000000 $
b101011000000000000000000 &
b1010111 "
b1010111 %
1#
#1740
0#
#1750
b1011000 "
b1011000 %
b101011100000000000000000 !
b101011100000000000000000 $
b101011100000000000000000 &
1#
#1760
0#
#1770
b101100000000000000000000 !
b101100000000000000000000 $
b101100000000000000000000 &
b1011001 "
b1011001 %
1#
#1780
0#
#1790
b1011010 "
b1011010 %
b101100100000000000000000 !
b101100100000000000000000 $
b101100100000000000000000 &
1#
#1800
0#
#1810
b101101000000000000000000 !
b101101000000000000000000 $
b101101000000000000000000 &
b1011011 "
b1011011 %
1#
#1820
0#
#1830
b1011100 "
b1011100 %
b101101100000000000000000 !
b101101100000000000000000 $
b101101100000000000000000 &
1#
#1840
0#
#1850
b101110000000000000000000 !
b101110000000000000000000 $
b101110000000000000000000 &
b1011101 "
b1011101 %
1#
#1860
0#
#1870
b1011110 "
b1011110 %
b101110100000000000000000 !
b101110100000000000000000 $
b101110100000000000000000 &
1#
#1880
0#
#1890
b101111000000000000000000 !
b101111000000000000000000 $
b101111000000000000000000 &
b1011111 "
b1011111 %
1#
#1900
0#
#1910
b1100000 "
b1100000 %
b101111100000000000000000 !
b101111100000000000000000 $
b101111100000000000000000 &
1#
#1920
0#
#1930
b110000000000000000000000 !
b110000000000000000000000 $
b110000000000000000000000 &
b1100001 "
b1100001 %
1#
#1940
0#
#1950
b1100010 "
b1100010 %
b110000100000000000000000 !
b110000100000000000000000 $
b110000100000000000000000 &
1#
#1960
0#
#1970
b110001000000000000000000 !
b110001000000000000000000 $
b110001000000000000000000 &
b1100011 "
b1100011 %
1#
#1980
0#
#1990
b1100100 "
b1100100 %
b110001100000000000000000 !
b110001100000000000000000 $
b110001100000000000000000 &
1#
#2000
0#
#2010
b110010000000000000000000 !
b110010000000000000000000 $
b110010000000000000000000 &
b1100101 "
b1100101 %
1#
#2020
0#
#2030
b1100110 "
b1100110 %
b110010100000000000000000 !
b110010100000000000000000 $
b110010100000000000000000 &
1#
#2040
0#
#2050
b110011000000000000000000 !
b110011000000000000000000 $
b110011000000000000000000 &
b1100111 "
b1100111 %
1#
#2060
0#
#2070
b1101000 "
b1101000 %
b110011100000000000000000 !
b110011100000000000000000 $
b110011100000000000000000 &
1#
#2080
0#
#2090
b110100000000000000000000 !
b110100000000000000000000 $
b110100000000000000000000 &
b1101001 "
b1101001 %
1#
#2100
0#
#2110
b1101010 "
b1101010 %
b110100100000000000000000 !
b110100100000000000000000 $
b110100100000000000000000 &
1#
#2120
0#
#2130
b110101000000000000000000 !
b110101000000000000000000 $
b110101000000000000000000 &
b1101011 "
b1101011 %
1#
#2140
0#
#2150
b1101100 "
b1101100 %
b110101100000000000000000 !
b110101100000000000000000 $
b110101100000000000000000 &
1#
#2160
0#
#2170
b110110000000000000000000 !
b110110000000000000000000 $
b110110000000000000000000 &
b1101101 "
b1101101 %
1#
#2180
0#
#2190
b1101110 "
b1101110 %
b110110100000000000000000 !
b110110100000000000000000 $
b110110100000000000000000 &
1#
#2200
0#
#2210
b110111000000000000000000 !
b110111000000000000000000 $
b110111000000000000000000 &
b1101111 "
b1101111 %
1#
#2220
0#
#2230
b1110000 "
b1110000 %
b110111100000000000000000 !
b110111100000000000000000 $
b110111100000000000000000 &
1#
#2240
0#
#2250
b111000000000000000000000 !
b111000000000000000000000 $
b111000000000000000000000 &
b1110001 "
b1110001 %
1#
#2260
0#
#2270
b1110010 "
b1110010 %
b111000100000000000000000 !
b111000100000000000000000 $
b111000100000000000000000 &
1#
#2280
0#
#2290
b111001000000000000000000 !
b111001000000000000000000 $
b111001000000000000000000 &
b1110011 "
b1110011 %
1#
#2300
0#
#2310
b1110100 "
b1110100 %
b111001100000000000000000 !
b111001100000000000000000 $
b111001100000000000000000 &
1#
#2320
0#
#2330
b111010000000000000000000 !
b111010000000000000000000 $
b111010000000000000000000 &
b1110101 "
b1110101 %
1#
#2340
0#
#2350
b1110110 "
b1110110 %
b111010100000000000000000 !
b111010100000000000000000 $
b111010100000000000000000 &
1#
#2360
0#
#2370
b111011000000000000000000 !
b111011000000000000000000 $
b111011000000000000000000 &
b1110111 "
b1110111 %
1#
#2380
0#
#2390
b1111000 "
b1111000 %
b111011100000000000000000 !
b111011100000000000000000 $
b111011100000000000000000 &
1#
#2400
0#
#2410
b111100000000000000000000 !
b111100000000000000000000 $
b111100000000000000000000 &
b1111001 "
b1111001 %
1#
#2420
0#
#2430
b1111010 "
b1111010 %
b111100100000000000000000 !
b111100100000000000000000 $
b111100100000000000000000 &
1#
#2440
0#
#2450
b111101000000000000000000 !
b111101000000000000000000 $
b111101000000000000000000 &
b1111011 "
b1111011 %
1#
#2460
0#
#2470
b1111100 "
b1111100 %
b111101100000000000000000 !
b111101100000000000000000 $
b111101100000000000000000 &
1#
#2480
0#
#2490
b111110000000000000000000 !
b111110000000000000000000 $
b111110000000000000000000 &
b1111101 "
b1111101 %
1#
#2500
0#
#2510
b1111110 "
b1111110 %
b111110100000000000000000 !
b111110100000000000000000 $
b111110100000000000000000 &
1#
#2520
0#
#2530
b111111000000000000000000 !
b111111000000000000000000 $
b111111000000000000000000 &
b1111111 "
b1111111 %
1#
#2540
0#
#2550
b10000000 "
b10000000 %
b111111100000000000000000 !
b111111100000000000000000 $
b111111100000000000000000 &
1#
#2560
0#
#2570
b100000000000000000000000 !
b100000000000000000000000 $
b100000000000000000000000 &
b10000001 "
b10000001 %
1#
#2580
0#
#2590
b10000010 "
b10000010 %
b100000010000000000000000 !
b100000010000000000000000 $
b100000010000000000000000 &
1#
#2600
0#
#2610
b100000100000000000000000 !
b100000100000000000000000 $
b100000100000000000000000 &
b10000011 "
b10000011 %
1#
#2620
0#
#2630
b10000100 "
b10000100 %
b100000110000000000000000 !
b100000110000000000000000 $
b100000110000000000000000 &
1#
#2640
0#
#2650
b100001000000000000000000 !
b100001000000000000000000 $
b100001000000000000000000 &
b10000101 "
b10000101 %
1#
#2660
0#
#2670
b10000110 "
b10000110 %
b100001010000000000000000 !
b100001010000000000000000 $
b100001010000000000000000 &
1#
#2680
0#
#2690
b100001100000000000000000 !
b100001100000000000000000 $
b100001100000000000000000 &
b10000111 "
b10000111 %
1#
#2700
0#
#2710
b10001000 "
b10001000 %
b100001110000000000000000 !
b100001110000000000000000 $
b100001110000000000000000 &
1#
#2720
0#
#2730
b100010000000000000000000 !
b100010000000000000000000 $
b100010000000000000000000 &
b10001001 "
b10001001 %
1#
#2740
0#
#2750
b10001010 "
b10001010 %
b100010010000000000000000 !
b100010010000000000000000 $
b100010010000000000000000 &
1#
#2760
0#
#2770
b100010100000000000000000 !
b100010100000000000000000 $
b100010100000000000000000 &
b10001011 "
b10001011 %
1#
#2780
0#
#2790
b10001100 "
b10001100 %
b100010110000000000000000 !
b100010110000000000000000 $
b100010110000000000000000 &
1#
#2800
0#
#2810
b100011000000000000000000 !
b100011000000000000000000 $
b100011000000000000000000 &
b10001101 "
b10001101 %
1#
#2820
0#
#2830
b10001110 "
b10001110 %
b100011010000000000000000 !
b100011010000000000000000 $
b100011010000000000000000 &
1#
#2840
0#
#2850
b100011100000000000000000 !
b100011100000000000000000 $
b100011100000000000000000 &
b10001111 "
b10001111 %
1#
#2860
0#
#2870
b10010000 "
b10010000 %
b100011110000000000000000 !
b100011110000000000000000 $
b100011110000000000000000 &
1#
#2880
0#
#2890
b100100000000000000000000 !
b100100000000000000000000 $
b100100000000000000000000 &
b10010001 "
b10010001 %
1#
#2900
0#
#2910
b10010010 "
b10010010 %
b100100010000000000000000 !
b100100010000000000000000 $
b100100010000000000000000 &
1#
#2920
0#
#2930
b100100100000000000000000 !
b100100100000000000000000 $
b100100100000000000000000 &
b10010011 "
b10010011 %
1#
#2940
0#
#2950
b10010100 "
b10010100 %
b100100110000000000000000 !
b100100110000000000000000 $
b100100110000000000000000 &
1#
#2960
0#
#2970
b100101000000000000000000 !
b100101000000000000000000 $
b100101000000000000000000 &
b10010101 "
b10010101 %
1#
#2980
0#
#2990
b10010110 "
b10010110 %
b100101010000000000000000 !
b100101010000000000000000 $
b100101010000000000000000 &
1#
#3000
0#
#3010
b100101100000000000000000 !
b100101100000000000000000 $
b100101100000000000000000 &
b10010111 "
b10010111 %
1#
#3020
0#
#3030
b10011000 "
b10011000 %
b100101110000000000000000 !
b100101110000000000000000 $
b100101110000000000000000 &
1#
#3040
0#
#3050
b100110000000000000000000 !
b100110000000000000000000 $
b100110000000000000000000 &
b10011001 "
b10011001 %
1#
#3060
0#
#3070
b10011010 "
b10011010 %
b100110010000000000000000 !
b100110010000000000000000 $
b100110010000000000000000 &
1#
#3080
0#
#3090
b100110100000000000000000 !
b100110100000000000000000 $
b100110100000000000000000 &
b10011011 "
b10011011 %
1#
#3100
0#
#3110
b10011100 "
b10011100 %
b100110110000000000000000 !
b100110110000000000000000 $
b100110110000000000000000 &
1#
#3120
0#
#3130
b100111000000000000000000 !
b100111000000000000000000 $
b100111000000000000000000 &
b10011101 "
b10011101 %
1#
#3140
0#
#3150
b10011110 "
b10011110 %
b100111010000000000000000 !
b100111010000000000000000 $
b100111010000000000000000 &
1#
#3160
0#
#3170
b100111100000000000000000 !
b100111100000000000000000 $
b100111100000000000000000 &
b10011111 "
b10011111 %
1#
#3180
0#
#3190
b10100000 "
b10100000 %
b100111110000000000000000 !
b100111110000000000000000 $
b100111110000000000000000 &
1#
#3200
0#
#3210
b101000000000000000000000 !
b101000000000000000000000 $
b101000000000000000000000 &
b10100001 "
b10100001 %
1#
#3220
0#
#3230
b10100010 "
b10100010 %
b101000010000000000000000 !
b101000010000000000000000 $
b101000010000000000000000 &
1#
#3240
0#
#3250
b101000100000000000000000 !
b101000100000000000000000 $
b101000100000000000000000 &
b10100011 "
b10100011 %
1#
#3260
0#
#3270
b10100100 "
b10100100 %
b101000110000000000000000 !
b101000110000000000000000 $
b101000110000000000000000 &
1#
#3280
0#
#3290
b101001000000000000000000 !
b101001000000000000000000 $
b101001000000000000000000 &
b10100101 "
b10100101 %
1#
#3300
0#
#3310
b10100110 "
b10100110 %
b101001010000000000000000 !
b101001010000000000000000 $
b101001010000000000000000 &
1#
#3320
0#
#3330
b101001100000000000000000 !
b101001100000000000000000 $
b101001100000000000000000 &
b10100111 "
b10100111 %
1#
#3340
0#
#3350
b10101000 "
b10101000 %
b101001110000000000000000 !
b101001110000000000000000 $
b101001110000000000000000 &
1#
#3360
0#
#3370
b101010000000000000000000 !
b101010000000000000000000 $
b101010000000000000000000 &
b10101001 "
b10101001 %
1#
#3380
0#
#3390
b10101010 "
b10101010 %
b101010010000000000000000 !
b101010010000000000000000 $
b101010010000000000000000 &
1#
#3400
0#
#3410
b101010100000000000000000 !
b101010100000000000000000 $
b101010100000000000000000 &
b10101011 "
b10101011 %
1#
#3420
0#
#3430
b10101100 "
b10101100 %
b101010110000000000000000 !
b101010110000000000000000 $
b101010110000000000000000 &
1#
#3440
0#
#3450
b101011000000000000000000 !
b101011000000000000000000 $
b101011000000000000000000 &
b10101101 "
b10101101 %
1#
#3460
0#
#3470
b10101110 "
b10101110 %
b101011010000000000000000 !
b101011010000000000000000 $
b101011010000000000000000 &
1#
#3480
0#
#3490
b101011100000000000000000 !
b101011100000000000000000 $
b101011100000000000000000 &
b10101111 "
b10101111 %
1#
#3500
0#
#3510
b10110000 "
b10110000 %
b101011110000000000000000 !
b101011110000000000000000 $
b101011110000000000000000 &
1#
#3520
0#
#3530
b101100000000000000000000 !
b101100000000000000000000 $
b101100000000000000000000 &
b10110001 "
b10110001 %
1#
#3540
0#
#3550
b10110010 "
b10110010 %
b101100010000000000000000 !
b101100010000000000000000 $
b101100010000000000000000 &
1#
#3560
0#
#3570
b101100100000000000000000 !
b101100100000000000000000 $
b101100100000000000000000 &
b10110011 "
b10110011 %
1#
#3580
0#
#3590
b10110100 "
b10110100 %
b101100110000000000000000 !
b101100110000000000000000 $
b101100110000000000000000 &
1#
#3600
0#
#3610
b101101000000000000000000 !
b101101000000000000000000 $
b101101000000000000000000 &
b10110101 "
b10110101 %
1#
#3620
0#
#3630
b10110110 "
b10110110 %
b101101010000000000000000 !
b101101010000000000000000 $
b101101010000000000000000 &
1#
#3640
0#
#3650
b101101100000000000000000 !
b101101100000000000000000 $
b101101100000000000000000 &
b10110111 "
b10110111 %
1#
#3660
0#
#3670
b10111000 "
b10111000 %
b101101110000000000000000 !
b101101110000000000000000 $
b101101110000000000000000 &
1#
#3680
0#
#3690
b101110000000000000000000 !
b101110000000000000000000 $
b101110000000000000000000 &
b10111001 "
b10111001 %
1#
#3700
0#
#3710
b10111010 "
b10111010 %
b101110010000000000000000 !
b101110010000000000000000 $
b101110010000000000000000 &
1#
#3720
0#
#3730
b101110100000000000000000 !
b101110100000000000000000 $
b101110100000000000000000 &
b10111011 "
b10111011 %
1#
#3740
0#
#3750
b10111100 "
b10111100 %
b101110110000000000000000 !
b101110110000000000000000 $
b101110110000000000000000 &
1#
#3760
0#
#3770
b101111000000000000000000 !
b101111000000000000000000 $
b101111000000000000000000 &
b10111101 "
b10111101 %
1#
#3780
0#
#3790
b10111110 "
b10111110 %
b101111010000000000000000 !
b101111010000000000000000 $
b101111010000000000000000 &
1#
#3800
0#
#3810
b101111100000000000000000 !
b101111100000000000000000 $
b101111100000000000000000 &
b10111111 "
b10111111 %
1#
#3820
0#
#3830
b11000000 "
b11000000 %
b101111110000000000000000 !
b101111110000000000000000 $
b101111110000000000000000 &
1#
#3840
0#
#3850
b110000000000000000000000 !
b110000000000000000000000 $
b110000000000000000000000 &
b11000001 "
b11000001 %
1#
#3860
0#
#3870
b11000010 "
b11000010 %
b110000010000000000000000 !
b110000010000000000000000 $
b110000010000000000000000 &
1#
#3880
0#
#3890
b110000100000000000000000 !
b110000100000000000000000 $
b110000100000000000000000 &
b11000011 "
b11000011 %
1#
#3900
0#
#3910
b11000100 "
b11000100 %
b110000110000000000000000 !
b110000110000000000000000 $
b110000110000000000000000 &
1#
#3920
0#
#3930
b110001000000000000000000 !
b110001000000000000000000 $
b110001000000000000000000 &
b11000101 "
b11000101 %
1#
#3940
0#
#3950
b11000110 "
b11000110 %
b110001010000000000000000 !
b110001010000000000000000 $
b110001010000000000000000 &
1#
#3960
0#
#3970
b110001100000000000000000 !
b110001100000000000000000 $
b110001100000000000000000 &
b11000111 "
b11000111 %
1#
#3980
0#
#3990
b11001000 "
b11001000 %
b110001110000000000000000 !
b110001110000000000000000 $
b110001110000000000000000 &
1#
#4000
0#
#4010
b110010000000000000000000 !
b110010000000000000000000 $
b110010000000000000000000 &
b11001001 "
b11001001 %
1#
#4020
0#
#4030
b11001010 "
b11001010 %
b110010010000000000000000 !
b110010010000000000000000 $
b110010010000000000000000 &
1#
#4040
0#
#4050
b110010100000000000000000 !
b110010100000000000000000 $
b110010100000000000000000 &
b11001011 "
b11001011 %
1#
#4060
0#
#4070
b11001100 "
b11001100 %
b110010110000000000000000 !
b110010110000000000000000 $
b110010110000000000000000 &
1#
#4080
0#
#4090
b110011000000000000000000 !
b110011000000000000000000 $
b110011000000000000000000 &
b11001101 "
b11001101 %
1#
#4100
0#
#4110
b11001110 "
b11001110 %
b110011010000000000000000 !
b110011010000000000000000 $
b110011010000000000000000 &
1#
#4120
0#
#4130
b110011100000000000000000 !
b110011100000000000000000 $
b110011100000000000000000 &
b11001111 "
b11001111 %
1#
#4140
0#
#4150
b11010000 "
b11010000 %
b110011110000000000000000 !
b110011110000000000000000 $
b110011110000000000000000 &
1#
#4160
0#
